integrate/__init__.py
integrate/gex.py
integrate/integrate.py
integrate/integrate_borehole.py
integrate/integrate_hdf5_info_cli.py
integrate/integrate_io.py
integrate/integrate_obsolete.py
integrate/integrate_plot.py
integrate/integrate_rejection.py
integrate/integrate_rejection_cli.py
integrate/integrate_timing_cli.py
integrate_module-0.91.dist-info/licenses/LICENSE
integrate_module-0.91.dist-info/METADATA
integrate_module-0.91.dist-info/WHEEL
integrate_module-0.91.dist-info/entry_points.txt
integrate_module-0.91.dist-info/top_level.txt
integrate_module-0.91.dist-info/RECORD
