Metadata-Version: 2.4
Name: integrate_module
Version: 0.91
Summary: Localized probabilistic data integration
Author-email: Thomas Mejer Hansen <tmeha@geo.au.dk>
License: MIT
Project-URL: Homepage, https://github.com/cultpenguin/integrate_module
Project-URL: Documentation, https://cultpenguin.github.io/integrate_module/
Project-URL: Repository, https://github.com/cultpenguin/integrate_module
Project-URL: Issues, https://github.com/cultpenguin/integrate_module/issues
Keywords: inversion,electromagnetic,geophysics,geology,prior,tarantola
Classifier: Programming Language :: Python :: 3
Requires-Python: >=3.10
License-File: LICENSE
Requires-Dist: numpy
Requires-Dist: matplotlib
Requires-Dist: h5py
Requires-Dist: scipy
Requires-Dist: psutil
Requires-Dist: tqdm
Requires-Dist: requests
Requires-Dist: geoprior1d>=0.9
Requires-Dist: ga-aem-forward-win; platform_system == "Windows"
Requires-Dist: jupyter>=1.0.0
Requires-Dist: jupytext
Requires-Dist: pandas
Requires-Dist: pyvista
Provides-Extra: dev
Requires-Dist: pytest; extra == "dev"
Requires-Dist: black; extra == "dev"
Dynamic: license-file
